moligeek/__init__.py
moligeek/__version__.py
moligeek/core/__init__.py
moligeek/core/LAN/__init__.py
moligeek/core/LAN/scan.py
moligeek/core/encode/__init__.py
moligeek/core/encode/decode.py
moligeek/core/encode/fence.py
moligeek/core/network/__init__.py
moligeek/core/network/hostinfo.py
moligeek/core/network/wifi.py
moligeek/core/text/__init__.py
moligeek/core/text/replace.py
moligeek/core/web/__init__.py
moligeek/core/web/imitate.py
moligeek/core/zip/__init__.py
moligeek/database/YiYan.dat
moligeek/path_dict/ASP.txt
moligeek/path_dict/ASPX.txt
moligeek/path_dict/DIR.txt
moligeek/path_dict/JSP.txt
moligeek/path_dict/MDB.txt
moligeek/path_dict/PHP.txt
moligeek/path_dict/__init__.py
moligeek-1.2.1.dist-info/LICENSE
moligeek-1.2.1.dist-info/METADATA
moligeek-1.2.1.dist-info/WHEEL
moligeek-1.2.1.dist-info/entry_points.txt
moligeek-1.2.1.dist-info/top_level.txt
moligeek-1.2.1.dist-info/RECORD
