Metadata-Version: 2.1
Name: moligeek
Version: 1.2.1
Summary: 一款逐渐完善的python集成工具,努力为开发者提供最大的便利
Home-page: https://github.com/yourmoln/moligeek
Author: yourmoln
Author-email: yourmoln@outlook.com
License: Apache 2.0
Classifier: Development Status :: 5 - Production/Stable
Classifier: Intended Audience :: Developers
Classifier: Topic :: Software Development :: Build Tools
Classifier: License :: OSI Approved :: Apache Software License
Classifier: Programming Language :: Python :: 3.8
Classifier: Programming Language :: Python :: 3.9
Classifier: Programming Language :: Python :: 3.10
Classifier: Programming Language :: Python :: 3.11
Classifier: Programming Language :: Python :: 3.12
Classifier: Programming Language :: Python :: 3.13
Requires-Python: >=3.8
License-File: LICENSE
Requires-Dist: requests
Requires-Dist: meo
Requires-Dist: beautifulsoup4
Requires-Dist: pywifi
Requires-Dist: comtypes
Requires-Dist: tqdm
Requires-Dist: asyncio
